<?xml version="1.0" encoding="utf-8" standalone="yes"?>
<post>
  <author>Admin</author>
  <title>Re: Resistance Art and Literature</title>
  <description />
  <content>&lt;p&gt;
When the world was still to be born&lt;br /&gt;
When Adam was still to receive his form &lt;br /&gt;
Then my relationship began [more]
&lt;/p&gt;
&lt;p&gt;
When I heard the Lord&amp;#39;s voice &lt;br /&gt;
A voice sweet and clear &lt;br /&gt;
I said &amp;quot;yes&amp;quot; with all my heart &lt;br /&gt;
And formed a bond with the land I love&lt;br /&gt;
&amp;nbsp;&lt;br /&gt;
Away I live in a mansion grand &lt;br /&gt;
But I long to campaign &lt;br /&gt;
On rocky roads &lt;br /&gt;
In bumpy jeep rides &lt;br /&gt;
With flags and banners &lt;br /&gt;
With selfless zeal to change &lt;br /&gt;
The sad present &lt;br /&gt;
Into a smiling future 
&lt;/p&gt;
&lt;p&gt;
I want to breathe the breath &lt;br /&gt;
Of home, &lt;br /&gt;
a breath both fair and fine &lt;br /&gt;
My spirit is in one place &lt;br /&gt;
My body in another &lt;br /&gt;
My mind torn asunder&lt;br /&gt;
&amp;nbsp;&lt;br /&gt;
Tyrant: do not offer comfort &lt;br /&gt;
Comfort leaves me cold &lt;br /&gt;
Much dearer do I hold &lt;br /&gt;
Marvi&amp;#39;s ancestral shawl &lt;br /&gt;
Symbol of our treasure&lt;br /&gt;
&amp;nbsp;&lt;br /&gt;
They thought it generous &lt;br /&gt;
To offer freedom for abandonment &lt;br /&gt;
The abandonment of a people, of a land &lt;br /&gt;
Of a struggle, of a dream &lt;br /&gt;
Of principles and of conscience &lt;br /&gt;
I thought it wrong&lt;br /&gt;
&amp;nbsp;&lt;br /&gt;
&amp;nbsp;&lt;br /&gt;
The cranes fly to their native hills &lt;br /&gt;
My heart longs to fly with them &lt;br /&gt;
Invisible chains &lt;br /&gt;
Hold me prisoner&lt;br /&gt;
&amp;nbsp;&lt;br /&gt;
The scent of the homeland &lt;br /&gt;
Wafts through the ocean air &lt;br /&gt;
Through continents &lt;br /&gt;
Its insistent call &lt;br /&gt;
A reverberating sound &lt;br /&gt;
Through sunset and dawn &lt;br /&gt;
Calling &lt;br /&gt;
Through walls &lt;br /&gt;
Calling &lt;br /&gt;
Through mountains &lt;br /&gt;
Seeking to reclaim &lt;br /&gt;
Its own&lt;br /&gt;
&amp;nbsp;&lt;br /&gt;
&amp;nbsp;&lt;br /&gt;
The land reclaims its own &lt;br /&gt;
When the dead die &lt;br /&gt;
They live again &lt;br /&gt;
Becoming part of a land&lt;br /&gt;
&amp;nbsp;&lt;br /&gt;
To my dear ones I say &lt;br /&gt;
Worry not &lt;br /&gt;
Shed no tears &lt;br /&gt;
Bear no regrets &lt;br /&gt;
These days will pass &lt;br /&gt;
After night comes day &lt;br /&gt;
After sorrow comes joy 
&lt;/p&gt;
&lt;p&gt;
The daughters of the desert know &lt;br /&gt;
That destiny &lt;br /&gt;
Cannot chain &lt;br /&gt;
The dream of a people free&lt;br /&gt;
&amp;nbsp;&lt;br /&gt;
&amp;nbsp;&lt;br /&gt;
The desert wind calls &lt;br /&gt;
Marvi calls &lt;br /&gt;
A timeless call &lt;br /&gt;
A call &lt;br /&gt;
The desert wind carries 
&lt;/p&gt;
&lt;p&gt;
Children: Hear the desert wind &lt;br /&gt;
Hear it whisper &lt;br /&gt;
Have faith &lt;br /&gt;
We will win 
&lt;/p&gt;
</content>
  <ispublished>True</ispublished>
  <isdeleted>False</isdeleted>
  <iscommentsenabled>True</iscommentsenabled>
  <pubDate>2008-01-17 07:17:00</pubDate>
  <lastModified>2008-01-17 07:19:22</lastModified>
  <raters>0</raters>
  <rating>0</rating>
  <slug>Re: Resistance Art and Literature</slug>
  <tags />
  <comments />
  <categories>
    <category>8a2286da-cc18-4aae-b739-40ac73041121</category>
  </categories>
  <notifications />
</post>