<?xml version="1.0" encoding="utf-8" standalone="yes"?>
<post>
  <author>Admin</author>
  <title>Musharraf’s Top Players Wiped Out</title>
  <description />
  <content>&lt;div id="showplayer"&gt;
&lt;object classid="clsid:d27cdb6e-ae6d-11cf-96b8-444553540000" codebase="http://download.macromedia.com/pub/shockwave/cabs/flash/swflash.cab#version=6,0,40,0" name="showplayer" width="400" height="255"&gt;
	&lt;param name="src" value="http://blip.tv/scripts/flash/showplayer.swf?enablejs=true&amp;amp;feedurl=http%3A%2F%2Fpkpolitics%2Eblip%2Etv%2Frss&amp;amp;file=http%3A%2F%2Fblip%2Etv%2Frss%2Fflash%2F684309&amp;amp;showplayerpath=http%3A%2F%2Fblip%2Etv%2Fscripts%2Fflash%2Fshowplayer%2Eswf" /&gt;
	&lt;param name="height" value="255" /&gt;
	&lt;param name="width" value="400" /&gt;
	&lt;param name="name" value="showplayer" /&gt;
	&lt;param name="quality" value="best" /&gt;
	&lt;embed type="application/x-shockwave-flash" src="http://blip.tv/scripts/flash/showplayer.swf?enablejs=true&amp;amp;feedurl=http%3A%2F%2Fpkpolitics%2Eblip%2Etv%2Frss&amp;amp;file=http%3A%2F%2Fblip%2Etv%2Frss%2Fflash%2F684309&amp;amp;showplayerpath=http%3A%2F%2Fblip%2Etv%2Fscripts%2Fflash%2Fshowplayer%2Eswf" height="255" width="400" name="showplayer" quality="best"&gt;&lt;/embed&gt;
&lt;/object&gt;
&lt;/div&gt;
</content>
  <ispublished>True</ispublished>
  <iscommentsenabled>True</iscommentsenabled>
  <pubDate>2008-02-18 19:04:00</pubDate>
  <lastModified>2008-02-18 19:07:07</lastModified>
  <raters>1</raters>
  <rating>5</rating>
  <slug>Musharraf’s Top Players Wiped Out</slug>
  <tags />
  <comments />
  <categories>
    <category>222c72c1-f8ad-4bc7-abda-823e95a8c9f7</category>
    <category>9be6af36-3704-4fb2-940e-f3fe8e4d9fea</category>
  </categories>
  <notifications />
</post>